tabtorch/__init__.py
tabtorch-0.0.0.dist-info/LICENSE
tabtorch-0.0.0.dist-info/WHEEL
tabtorch-0.0.0.dist-info/METADATA
tabtorch-0.0.0.dist-info/RECORD
